{"assets/HSGG_Logo.png":["assets/HSGG_Logo.png"],"assets/Hero_background.webp":["assets/Hero_background.webp"],"assets/Hero_grafic.png":["assets/Hero_grafic.png"],"assets/Hero_grafik.webp":["assets/Hero_grafik.webp"],"assets/coins.webp":["assets/coins.webp"],"assets/fonts/aptos.ttf":["assets/fonts/aptos.ttf"],"assets/fonts/verdana.ttf":["assets/fonts/verdana.ttf"],"assets/night_sky.webp":["assets/night_sky.webp"],"assets/scroll.webp":["assets/scroll.webp"],"assets/scroll_shadow.webp":["assets/scroll_shadow.webp"],"assets/settings.webp":["assets/settings.webp"],"assets/store/Amphora.png":["assets/store/Amphora.png"],"assets/store/Amphora2.png":["assets/store/Amphora2.png"],"assets/store/AmphoraBroken.png":["assets/store/AmphoraBroken.png"],"assets/store/AmphoraBroken2.png":["assets/store/AmphoraBroken2.png"],"assets/store/Armor.png":["assets/store/Armor.png"],"assets/store/Banner.png":["assets/store/Banner.png"],"assets/store/BannerChiro.png":["assets/store/BannerChiro.png"],"assets/store/Bus2tOld.png":["assets/store/Bus2tOld.png"],"assets/store/Bust.png":["assets/store/Bust.png"],"assets/store/Bust2.png":["assets/store/Bust2.png"],"assets/store/BustOld.png":["assets/store/BustOld.png"],"assets/store/CenturionHelmet.png":["assets/store/CenturionHelmet.png"],"assets/store/CenturionHelmet2.png":["assets/store/CenturionHelmet2.png"],"assets/store/CenturionHelmetBronze.png":["assets/store/CenturionHelmetBronze.png"],"assets/store/CenturionHelmetBronze2.png":["assets/store/CenturionHelmetBronze2.png"],"assets/store/CoinBronze.png":["assets/store/CoinBronze.png"],"assets/store/CoinGold.png":["assets/store/CoinGold.png"],"assets/store/CoinSilver.png":["assets/store/CoinSilver.png"],"assets/store/Colloseum.png":["assets/store/Colloseum.png"],"assets/store/ColloseumNew.png":["assets/store/ColloseumNew.png"],"assets/store/Column.png":["assets/store/Column.png"],"assets/store/Column2.png":["assets/store/Column2.png"],"assets/store/Emperor.png":["assets/store/Emperor.png"],"assets/store/Gear.png":["assets/store/Gear.png"],"assets/store/Grapes.png":["assets/store/Grapes.png"],"assets/store/Insula.png":["assets/store/Insula.png"],"assets/store/Laurels.png":["assets/store/Laurels.png"],"assets/store/LaurelsBronze.png":["assets/store/LaurelsBronze.png"],"assets/store/LaurelsGold.png":["assets/store/LaurelsGold.png"],"assets/store/LaurelsSilver.png":["assets/store/LaurelsSilver.png"],"assets/store/Legionnaire.png":["assets/store/Legionnaire.png"],"assets/store/Obelisk.png":["assets/store/Obelisk.png"],"assets/store/Obelisk2.png":["assets/store/Obelisk2.png"],"assets/store/Roman.png":["assets/store/Roman.png"],"assets/store/RomanOld.png":["assets/store/RomanOld.png"],"assets/store/RomanOld_.png":["assets/store/RomanOld_.png"],"assets/store/RomanWoman.png":["assets/store/RomanWoman.png"],"assets/store/Roman_.png":["assets/store/Roman_.png"],"assets/store/Scroll.png":["assets/store/Scroll.png"],"assets/store/Scroll2.png":["assets/store/Scroll2.png"],"assets/store/Senate.png":["assets/store/Senate.png"],"assets/store/Senate_.png":["assets/store/Senate_.png"],"assets/store/Shield.png":["assets/store/Shield.png"],"assets/store/Temple.png":["assets/store/Temple.png"],"assets/store/Villa.png":["assets/store/Villa.png"],"assets/store/flag.png":["assets/store/flag.png"],"assets/store/flagChiro.png":["assets/store/flagChiro.png"],"assets/store/flagSPQR.png":["assets/store/flagSPQR.png"],"assets/test.webp":["assets/test.webp"],"assets/user_profile.webp":["assets/user_profile.webp"],"assets/xp_banner.webp":["assets/xp_banner.webp"],"packages/cupertino_icons/assets/CupertinoIcons.ttf":["packages/cupertino_icons/assets/CupertinoIcons.ttf"]}